# K8s 命令

1、查看k8s的运行的所有pods

```shell
kubectl get pods,svc -n dfcx-dev -o wide
```

2、进入容器

```shell
kubectl exec -it -n dfcx-dev commserv-smsterrace-biz-b5f5d8bc-zpn4h bash
```

3 、





# kafka命令

1、windows启动kafka

```shell
# 启动zookeeper
.\bin\windows\zookeeper-server-start.bat .\config\zookeeper.properties
# 启动kafka
.\bin\windows\kafka-server-start.bat .\config\server.properties
```

2、查看相关topic的日志

```shell
./kafka-console-consumer.sh --bootstrap-server 10.120.2.15:9092 --topic tsms003 --from-beginning
```





# Linux 命令

1、查看相关服务的进程

```shell
# 查看java进程
ps -ef | grep java
# 列表出所有进程
ps -ef
# 列出和当前用户有关的进程
ps -l
# 查看某一用户的进程状态
ps -u user

# 查看进程号所占用的端口号
netstat -nltp | grep  mysql

```

2、查看日志文件

```shell
# 筛选2020-09-02的所有zip包
zgrep -c '"vehicleID":"27197"' `ls | grep 2020-09-02`
```

3、查看系统信息

```shell
# 查看系统内核信息
uname -a

# 查看系统版本
lsb_release -a
```

4、压缩解压文件

```shell
tar -zxvf 压缩文件名
```

## vim 操作命令

```shell
# 显示所有行
:set su

# 多行删除
d + 行数 + d

# 复制一行
y+y+p
```



# Windows 命令

1、进程相关

```shell
# 查看所有进程
netstat -ano
# 输入指令找到对应的进程
tasklist | findstr "7676"
# 杀死进程
taskkill /f /t /im java.exe
```





# go命令

1、protoc 转译对应的pb文件

```shell
protoc --java_out =. simple.proto
protoc --go_out =. simple.proto

```

2、启动服务

```shell
# 启动notify服务
nohup ./notify-router -c router.conf 2>&1 > logs/router.log &
nohup ./notify-comet -c comet.conf 2>&1 > logs/comet.log &
nohup ./notify-logic -c logic.conf 2>&1 > logs/logic.log &
nohup ./notify-web -c web.conf 2>&1 > logs/web.log &

# 启动push服务
nohup ./push-router -c router.conf 2>&1 > logs/router.log &
nohup ./push-comet -c comet.conf 2>&1 > logs/comet.log &
nohup ./push-logic -c logic.conf 2>&1 > logs/logic.log &

# 启动notify服务
nohup ./upload-router -c router.conf 2>&1 > logs/router.log &
nohup ./upload-driver -c comet.conf 2>&1 > logs/comet.log &
nohup ./upload-logic -c logic.conf 2>&1 > logs/logic.log &
```





# mysql 命令

1、连接mysql数据库

```shell
# 连接mysql
mysql -u root -p
```

2、索引

```mysql
# 创建索引
CREATE  [UNIQUE ]  INDEX [indexName] ON table_name(column))

# 删除索引
DROP INDEX [indexName] ON mytable;

#查看索引
SHOW INDEX FROM table_name\G

-- PRIMARY  KEY（主键索引）
ALTER  TABLE  `table_name`  ADD  PRIMARY  KEY (  `column`  ) 
-- UNIQUE(唯一索引)
ALTER  TABLE  `table_name`  ADD  UNIQUE (`column` ) 
-- INDEX(普通索引)
ALTER  TABLE  `table_name`  ADD  INDEX index_name (  `column`  )
-- FULLTEXT(全文索引)
ALTER  TABLE  `table_name`  ADD  FULLTEXT ( `column` )
-- 多列索引
ALTER  TABLE  `table_name`  ADD  INDEX index_name (  `column1`,  `column2`,  `column3`  )
```

3、查看SQL的执行过程（https://blog.csdn.net/n88Lpo/article/details/107872783）

```mysql
# optimizer_trace是一个跟踪功能，跟踪执行的语句的解析优化执行的过程，并将跟踪到的信息记录到INFORMATION_SCHEMA.OPTIMIZER_TRACE表中
SHOW VARIABLES LIKE '%optimizer_trace%';
set optimizer_trace="enabled=on"; 
set optimizer_trace_max_mem_size=1000000;
select count(*) from renter_info where renter_risk_score >= 90 and  renter_risk_score <= 91 and del_state = 0
;
select * from information_schema.optimizer_trace;
```

4、查看mysql的相关信息

```mysql
# 查看mysql提供的所有存储引擎
show engines;
# 查看默认的存储引擎
show variables like '%storage_engine%';
# 查看某个表的信息
show table status like "renter_info";

# 查看sql_mode
SHOW VARIABLES LIKE 'sql_mode';
```

5、用户权限管理

```mysql
# 查看mysql的user表
use mysql;
# 查看所有用户的信息
select host,user,authentication_string,select_priv,insert_priv,drop_priv from mysql.user;

# host ：表示连接类型
#		% 表示所有远程通过 TCP方式的连接
#        IP 地址 如 (192.168.1.2,127.0.0.1) 通过制定ip地址进行的TCP方式的连接
#       机器名   通过制定i网络中的机器名进行的TCP方式的连接
#        ::1   IPv6的本地ip地址  等同于IPv4的 127.0.0.1
#       localhost 本地方式通过命令行方式的连接 ，比如mysql -u xxx -p 123xxx 方式的连接。
#  User:表示用户名
#       同一用户通过不同方式链接的权限是不一样的。
#  
#  password ： 密码
#       所有密码串通过 password(明文字符串) 生成的密文字符串。加密算法为MYSQLSHA1 ，不可逆 。
#        mysql 5.7 的密码保存到 authentication_string 字段中不再使用password 字段。
# 
#  select_priv , insert_priv等 
#        为该用户所拥有的权限。

#创建用户
create user lijiat identified by '123123';

# 修改当前用户的密码
set password =password('123456')

# 修改某一个用户的密码
update mysql.user set password=password('123456') where user='li4';
# 修改密码之后一定要执行强制更新操作，所有通过user表的修改，必须用该命令才能生效。
flush privileges; 

# 修改用户名
update mysql.user set user='li4' where user='wang5';
flush privileges;

# 删除用户
drop user li4 ;

####################### 权限管理 ###############################
# 授权命令（该权限如果发现没有该用户，则会直接新建一个用户。）
grant 权限1,权限2,…权限n on 数据库名称.表名称 to 用户名@用户地址 identified by ‘连接口令’;

# 例如（给li4用户用本地命令行方式下，授予atguigudb这个库下的所有表的插删改查的权限。）
grant select,insert,delete,drop on atguigudb.* to li4@localhost  ;

# 授予通过网络方式登录的的joe用户 ，对所有库所有表的全部权限，密码设为123.
grant all privileges on *.* to joe@'%'  identified by '123'; 

# 查看当前用户的权限
show grants;

# 收回用户权限（必须用户重新登录后才能生效）
revoke  权限1,权限2,…权限n on 数据库名称.表名称  from  用户名@用户地址 ;

# 收回 joe用户全库全表的所有权限
REVOKE ALL PRIVILEGES ON mysql.* FROM joe@localhost;

# 收回joe用户在mysql库下的所有表的插删改查权限
REVOKE select,insert,update,delete ON mysql.* FROM joe@localhost;
```

6、查看mysql的执行周期

```mysql
#  修改配置文件/etc/my.cnf
# query_cache_type=1
# 重启mysql
# 查看 profiling 的状态
    show variables like '%profiling%';
# 设置profiling
set profiling=1;
# 执行查询语句
select * from xxx ;
# 显示最近的几次查询
show profiles;
# 查看程序的执行步骤
show profile cpu,block io for query 编号  
```

7、 查询语句

```mysql
# SQL_NO_CACHE 查询不经过缓存
SELECT SQL_NO_CACHE * FROM emp WHERE emp.age=30
```





# mongo 命令

1、创建数据库

```shell
use DATABASE_NAME
```

2、创建集合

```shell
db.createCollection(name, options)
例：
	db.createCollection("student", { name : "zhang", age : 18 } )
```

3、插入文档

```shell
db.COLLECTION_NAME.insert(document)
```

4、查询文档

```shell
db.collection.find(query, projection)

# 查询某个时间段的数据
db.position_state_history.find({vehiclePlateNum:"鄂AD29762",createTime:{$gt:"2019-06-04 09:00:00 000",$lt:"2019-06-04 13:00:00 000"}})
```



# git 命令



```shell
# 查看代码修改状态
git status

# 查看远程仓库的地址
git remote -v

# 删除远程仓库地址
git remote rm origin

# 提交代码到本地仓库
git commit -m "first commit"

# 推送提交的代码到远程仓库
git push -u origin master

# 增加远程仓库地址
git remote add origin https://github.com/Lijatu/maven-demo.git
```



# redis 命令

1、连接redis

```shell
# 开启redis服务
redis-server
# 连接redis服务器
redis-cli -h host -p port
# 连接redis服务器
redis-cli -h host -p port -a password
# 集群
redis-cli -h host -c

```

2、字符串

```shell
set key value
get key
```

3、哈希

```shell
hset key field value [field value ...]
hget key field
```

4、List

```shell
# 从右边插入字符串
rpush key value 		
# 从左边插入字符串
lpush key value 		
lrange key start stop
```

5、Set集合

```shell
sadd key value
smembers key
```

6、Zset(sorted set:有序集合)

```shell
zadd key score member
zrange key start stop
zrangebyscore key satrt stop
```

7、redis key命令

```shell
del key						//该命令用于在 key 存在时删除 key。
dump key					//序列化给定 key ，并返回被序列化的值。
exists key 					//检查给定 key 是否存在。
expire key seconds			//为给定 key 设置过期时间，以秒计
expireat key timestamp		//设置 key 过期时间的时间戳(unix timestamp)以秒计
pexpire key milliseconds	//设置 key 的过期时间以毫秒计。
pexpireat key timestamp 	//设置 key 过期时间的时间戳(unix timestamp)以毫秒计
keys pattern				//查找所有符合给定模式( pattern)的 key
move key db					//将当前数据库的 key 移动到给定的数据库 db 当中。
persist key 				//移除 key 的过期时间，key 将持久保持。
pttl key					//以毫秒为单位返回 key 的剩余的过期时间
rename key newkey			//修改key的名称
renamenx key newkey			//仅当newkey不存在时，在将key的名称更改为key
type key					//返回key所存储的值的类型
```

8、redis 订阅

```shell
subscribe channelName			//创建频道
publish channelName	“message”	//在频道中发送消息
```

9、redis 事务

```shell
multi  		用于标记事物的开始
exec		执行在一个事物内命令队列中所有命令，同时将当前的连接状态恢复为正常状态
discard 	回滚事物中的所有命令
witch key 	在multi之前，指定监控的keys
unwatch		取消当前事物中指定监控的keys
```

# 字节码指令

| 字节码 | 助记符          | 指令含义                                                     |
| ------ | --------------- | ------------------------------------------------------------ |
| 0x00   | nop             | None                                                         |
| 0x01   | aconst_null     | 将null推送至栈顶                                             |
| 0x02   | iconst_m1       | 将int型-1推送至栈顶                                          |
| 0x03   | iconst_0        | 将int型0推送至栈顶                                           |
| 0x04   | iconst_1        | 将int型1推送至栈顶                                           |
| 0x05   | iconst_2        | 将int型2推送至栈顶                                           |
| 0x06   | iconst_3        | 将int型3推送至栈顶                                           |
| 0x07   | iconst_4        | 将int型4推送至栈顶                                           |
| 0x08   | iconst_5        | 将int型5推送至栈顶                                           |
| 0x09   | lconst_0        | 将long型0推送至栈顶                                          |
| 0x0a   | lconst_1        | 将long型1推送至栈顶                                          |
| 0x0b   | fconst_0        | 将float型0推送至栈顶                                         |
| 0x0c   | fconst_1        | 将float型1推送至栈顶                                         |
| 0x0d   | fconst_2        | 将float型2推送至栈顶                                         |
| 0x0e   | dconst_0        | 将double型0推送至栈顶                                        |
| 0x0f   | dconst_1        | 将double型1推送至栈顶                                        |
| 0x10   | bipush          | 将单字节的常量值(-128~127)推送至栈顶                         |
| 0x11   | sipush          | 将一个短整型常量(-32768~32767)推送至栈顶                     |
| 0x12   | ldc             | 将int,float或String型常量值从常量池中推送至栈顶              |
| 0x13   | ldc_w           | 将int,float或String型常量值从常量池中推送至栈顶(宽索引)      |
| 0x14   | ldc2_w          | 将long或double型常量值从常量池中推送至栈顶(宽索引)           |
| 0x15   | iload           | 将指定的int型本地变量推送至栈顶                              |
| 0x16   | lload           | 将指定的long型本地变量推送至栈顶                             |
| 0x17   | fload           | 将指定的float型本地变量推送至栈顶                            |
| 0x18   | dload           | 将指定的double型本地变量推送至栈顶                           |
| 0x19   | aload           | 将指定的引用类型本地变量推送至栈顶                           |
| 0x1a   | iload_0         | 将第一个int型本地变量推送至栈顶                              |
| 0x1b   | iload_1         | 将第二个int型本地变量推送至栈顶                              |
| 0x1c   | iload_2         | 将第三个int型本地变量推送至栈顶                              |
| 0x1d   | iload_3         | 将第四个int型本地变量推送至栈顶                              |
| 0x1e   | lload_0         | 将第一个long型本地变量推送至栈顶                             |
| 0x1f   | lload_1         | 将第二个long型本地变量推送至栈顶                             |
| 0x20   | lload_2         | 将第三个long型本地变量推送至栈顶                             |
| 0x21   | lload_3         | 将第四个long型本地变量推送至栈顶                             |
| 0x22   | fload_0         | 将第一个float型本地变量推送至栈顶                            |
| 0x23   | fload_1         | 将第二个float型本地变量推送至栈顶                            |
| 0x24   | fload_2         | 将第三个float型本地变量推送至栈顶                            |
| 0x25   | fload_3         | 将第四个float型本地变量推送至栈顶                            |
| 0x26   | dload_0         | 将第一个double型本地变量推送至栈顶                           |
| 0x27   | dload_1         | 将第二个double型本地变量推送至栈顶                           |
| 0x28   | dload_2         | 将第三个double型本地变量推送至栈顶                           |
| 0x29   | dload_3         | 将第四个double型本地变量推送至栈顶                           |
| 0x2a   | aload_0         | 将第一个引用类型本地变量推送至栈顶                           |
| 0x2b   | aload_1         | 将第二个引用类型本地变量推送至栈顶                           |
| 0x2c   | aload_2         | 将第三个引用类型本地变量推送至栈顶                           |
| 0x2d   | aload_3         | 将第四个引用类型本地变量推送至栈顶                           |
| 0x2e   | iaload          | 将int型数组指定索引的值推送至栈顶                            |
| 0x2f   | laload          | 将long型数组指定索引的值推送至栈顶                           |
| 0x30   | faload          | 将float型数组指定索引的值推送至栈顶                          |
| 0x31   | daload          | 将double型数组指定索引的值推送至栈顶                         |
| 0x32   | aaload          | 将引用类型数组指定索引的值推送至栈顶                         |
| 0x33   | baload          | 将boolean或byte型数组指定索引的值推送至栈顶                  |
| 0x34   | caload          | 将char型数组指定索引的值推送至栈顶                           |
| 0x35   | saload          | 将short型数组指定索引的值推送至栈顶                          |
| 0x36   | istore          | 将栈顶int型数值存入指定本地变量                              |
| 0x37   | lstore          | 将栈顶long型数值存入指定本地变量                             |
| 0x38   | fstore          | 将栈顶float型数值存入指定本地变量                            |
| 0x39   | dstore          | 将栈顶double型数值存入指定本地变量                           |
| 0x3a   | astore          | 将栈顶引用类型数值存入指定本地变量                           |
| 0x3b   | istore_0        | 将栈顶int型数值存入第一个本地变量                            |
| 0x3c   | istore_1        | 将栈顶int型数值存入第二个本地变量                            |
| 0x3d   | istore_2        | 将栈顶int型数值存入第三个本地变量                            |
| 0x3e   | istore_3        | 将栈顶int型数值存入第四个本地变量                            |
| 0x3f   | lstore_0        | 将栈顶long型数值存入第一个本地变量                           |
| 0x40   | lstore_1        | 将栈顶long型数值存入第二个本地变量                           |
| 0x41   | lstore_2        | 将栈顶long型数值存入第三个本地变量                           |
| 0x42   | lstore_3        | 将栈顶long型数值存入第四个本地变量                           |
| 0x43   | fstore_0        | 将栈顶float型数值存入第一个本地变量                          |
| 0x44   | fstore_1        | 将栈顶float型数值存入第二个本地变量                          |
| 0x45   | fstore_2        | 将栈顶float型数值存入第三个本地变量                          |
| 0x46   | fstore_3        | 将栈顶float型数值存入第四个本地变量                          |
| 0x47   | dstore_0        | 将栈顶double型数值存入第一个本地变量                         |
| 0x48   | dstore_1        | 将栈顶double型数值存入第二个本地变量                         |
| 0x49   | dstore_2        | 将栈顶double型数值存入第三个本地变量                         |
| 0x4a   | dstore_3        | 将栈顶double型数值存入第四个本地变量                         |
| 0x4b   | astore_0        | 将栈顶引用型数值存入第一个本地变量                           |
| 0x4c   | astore_1        | 将栈顶引用型数值存入第二个本地变量                           |
| 0x4d   | astore_2        | 将栈顶引用型数值存入第三个本地变量                           |
| 0x4e   | astore_3        | 将栈顶引用型数值存入第四个本地变量                           |
| 0x4f   | iastore         | 将栈顶int型数值存入指定数组的指定索引位置                    |
| 0x50   | lastore         | 将栈顶long型数值存入指定数组的指定索引位置                   |
| 0x51   | fastore         | 将栈顶float型数值存入指定数组的指定索引位置                  |
| 0x52   | dastore         | 将栈顶double型数值存入指定数组的指定索引位置                 |
| 0x53   | aastore         | 将栈顶引用型数值存入指定数组的指定索引位置                   |
| 0x54   | bastore         | 将栈顶boolean或byte型数值存入指定数组的指定索引位置          |
| 0x55   | castore         | 将栈顶char型数值存入指定数组的指定索引位置                   |
| 0x56   | sastore         | 将栈顶short型数值存入指定数组的指定索引位置                  |
| 0x57   | pop             | 将栈顶数值弹出(数值不能是long或double类型的)                 |
| 0x58   | pop2            | 将栈顶的一个(对于非long或double类型)或两个数值(对于非long或double的其他类型)弹出 |
| 0x59   | dup             | 复制栈顶数值并将复制值压入栈顶                               |
| 0x5a   | dup_x1          | 复制栈顶数值并将两个复制值压入栈顶                           |
| 0x5b   | dup_x2          | 复制栈顶数值并将三个(或两个)复制值压入栈顶                   |
| 0x5c   | dup2            | 复制栈顶一个(对于long或double类型)或两个(对于非long或double的其他类型)数值并将复制值压入栈顶 |
| 0x5d   | dup2_x1         | dup_x1指令的双倍版本                                         |
| 0x5e   | dup2_x2         | dup_x2指令的双倍版本                                         |
| 0x5f   | swap            | 将栈顶最顶端的两个数值互换(数值不能是long或double类型)       |
| 0x60   | iadd            | 将栈顶两int型数值相加并将结果压入栈顶                        |
| 0x61   | ladd            | 将栈顶两long型数值相加并将结果压入栈顶                       |
| 0x62   | fadd            | 将栈顶两float型数值相加并将结果压入栈顶                      |
| 0x63   | dadd            | 将栈顶两double型数值相加并将结果压入栈顶                     |
| 0x64   | isub            | 将栈顶两int型数值相减并将结果压入栈顶                        |
| 0x65   | lsub            | 将栈顶两long型数值相减并将结果压入栈顶                       |
| 0x66   | fsub            | 将栈顶两float型数值相减并将结果压入栈顶                      |
| 0x67   | dsub            | 将栈顶两double型数值相减并将结果压入栈顶                     |
| 0x68   | imul            | 将栈顶两int型数值相乘并将结果压入栈顶                        |
| 0x69   | lmul            | 将栈顶两long型数值相乘并将结果压入栈顶                       |
| 0x6a   | fmul            | 将栈顶两float型数值相乘并将结果压入栈顶                      |
| 0x6b   | dmul            | 将栈顶两double型数值相乘并将结果压入栈顶                     |
| 0x6c   | idiv            | 将栈顶两int型数值相除并将结果压入栈顶                        |
| 0x6d   | ldiv            | 将栈顶两long型数值相除并将结果压入栈顶                       |
| 0x6e   | fdiv            | 将栈顶两float型数值相除并将结果压入栈顶                      |
| 0x6f   | ddiv            | 将栈顶两double型数值相除并将结果压入栈顶                     |
| 0x70   | irem            | 将栈顶两int型数值作取模运算并将结果压入栈顶                  |
| 0x71   | lrem            | 将栈顶两long型数值作取模运算并将结果压入栈顶                 |
| 0x72   | frem            | 将栈顶两float型数值作取模运算并将结果压入栈顶                |
| 0x73   | drem            | 将栈顶两double型数值作取模运算并将结果压入栈顶               |
| 0x74   | ineg            | 将栈顶int型数值取负并将结果压入栈顶                          |
| 0x75   | lneg            | 将栈顶long型数值取负并将结果压入栈顶                         |
| 0x76   | fneg            | 将栈顶float型数值取负并将结果压入栈顶                        |
| 0x77   | dneg            | 将栈顶double型数值取负并将结果压入栈顶                       |
| 0x78   | ishl            | 将int型数值左移指定位数并将结果压入栈顶                      |
| 0x79   | lshl            | 将long型数值左移指定位数并将结果压入栈顶                     |
| 0x7a   | ishr            | 将int型数值右(带符号)移指定位数并将结果压入栈顶              |
| 0x7b   | lshr            | 将long型数值右(带符号)移指定位数并将结果压入栈顶             |
| 0x7c   | iushr           | 将int型数值右(无符号)移指定位数并将结果压入栈顶              |
| 0x7d   | lushr           | 将long型数值右(无符号)移指定位数并将结果压入栈顶             |
| 0x7e   | iand            | 将栈顶两int型数值"按位与"并将结果压入栈顶                    |
| 0x7f   | land            | 将栈顶两long型数值"按位与"并将结果压入栈顶                   |
| 0x80   | ior             | 将栈顶两int型数值"按位或"并将结果压入栈顶                    |
| 0x81   | lor             | 将栈顶两long型数值"按位或"并将结果压入栈顶                   |
| 0x82   | ixor            | 将栈顶两int型数值"按位异或"并将结果压入栈顶                  |
| 0x83   | lxor            | 将栈顶两long型数值"按位异或"并将结果压入栈顶                 |
| 0x84   | iinc            | 将指定int型变量增加指定值(如i++, i--, i+=2等)                |
| 0x85   | i2l             | 将栈顶int型数值强制转换为long型数值并将结果压入栈顶          |
| 0x86   | i2f             | 将栈顶int型数值强制转换为float型数值并将结果压入栈顶         |
| 0x87   | i2d             | 将栈顶int型数值强制转换为double型数值并将结果压入栈顶        |
| 0x88   | l2i             | 将栈顶long型数值强制转换为int型数值并将结果压入栈顶          |
| 0x89   | l2f             | 将栈顶long型数值强制转换为float型数值并将结果压入栈顶        |
| 0x8a   | l2d             | 将栈顶long型数值强制转换为double型数值并将结果压入栈顶       |
| 0x8b   | f2i             | 将栈顶float型数值强制转换为int型数值并将结果压入栈顶         |
| 0x8c   | f2l             | 将栈顶float型数值强制转换为long型数值并将结果压入栈顶        |
| 0x8d   | f2d             | 将栈顶float型数值强制转换为double型数值并将结果压入栈顶      |
| 0x8e   | d2i             | 将栈顶double型数值强制转换为int型数值并将结果压入栈顶        |
| 0x8f   | d2l             | 将栈顶double型数值强制转换为long型数值并将结果压入栈顶       |
| 0x90   | d2f             | 将栈顶double型数值强制转换为float型数值并将结果压入栈顶      |
| 0x91   | i2b             | 将栈顶int型数值强制转换为byte型数值并将结果压入栈顶          |
| 0x92   | i2c             | 将栈顶int型数值强制转换为char型数值并将结果压入栈顶          |
| 0x93   | i2s             | 将栈顶int型数值强制转换为short型数值并将结果压入栈顶         |
| 0x94   | lcmp            | 比较栈顶两long型数值大小, 并将结果(1, 0或-1)压入栈顶         |
| 0x95   | fcmpl           | 比较栈顶两float型数值大小, 并将结果(1, 0或-1)压入栈顶; 当其中一个数值为`NaN`时, 将-1压入栈顶 |
| 0x96   | fcmpg           | 比较栈顶两float型数值大小, 并将结果(1, 0或-1)压入栈顶; 当其中一个数值为`NaN`时, 将1压入栈顶 |
| 0x97   | dcmpl           | 比较栈顶两double型数值大小, 并将结果(1, 0或-1)压入栈顶; 当其中一个数值为`NaN`时, 将-1压入栈顶 |
| 0x98   | dcmpg           | 比较栈顶两double型数值大小, 并将结果(1, 0或-1)压入栈顶; 当其中一个数值为`NaN`时, 将1压入栈顶 |
| 0x99   | ifeq            | 当栈顶int型数值等于0时跳转                                   |
| 0x9a   | ifne            | 当栈顶int型数值不等于0时跳转                                 |
| 0x9b   | iflt            | 当栈顶int型数值小于0时跳转                                   |
| 0x9c   | ifge            | 当栈顶int型数值大于等于0时跳转                               |
| 0x9d   | ifgt            | 当栈顶int型数值大于0时跳转                                   |
| 0x9e   | ifle            | 当栈顶int型数值小于等于0时跳转                               |
| 0x9f   | if_icmpeq       | 比较栈顶两int型数值大小, 当结果等于0时跳转                   |
| 0xa0   | if_icmpne       | 比较栈顶两int型数值大小, 当结果不等于0时跳转                 |
| 0xa1   | if_icmplt       | 比较栈顶两int型数值大小, 当结果小于0时跳转                   |
| 0xa2   | if_icmpge       | 比较栈顶两int型数值大小, 当结果大于等于0时跳转               |
| 0xa3   | if_icmpgt       | 比较栈顶两int型数值大小, 当结果大于0时跳转                   |
| 0xa4   | if_icmple       | 比较栈顶两int型数值大小, 当结果小于等于0时跳转               |
| 0xa5   | if_acmpeq       | 比较栈顶两引用型数值, 当结果相等时跳转                       |
| 0xa6   | if_acmpne       | 比较栈顶两引用型数值, 当结果不相等时跳转                     |
| 0xa7   | goto            | 无条件跳转                                                   |
| 0xa8   | jsr             | 跳转至指定的16位offset位置, 并将jsr的下一条指令地址压入栈顶  |
| 0xa9   | ret             | 返回至本地变量指定的index的指令位置(一般与jsr或jsr_w联合使用) |
| 0xaa   | tableswitch     | 用于switch条件跳转, case值连续(可变长度指令)                 |
| 0xab   | lookupswitch    | 用于switch条件跳转, case值不连续(可变长度指令)               |
| 0xac   | ireturn         | 从当前方法返回int                                            |
| 0xad   | lreturn         | 从当前方法返回long                                           |
| 0xae   | freturn         | 从当前方法返回float                                          |
| 0xaf   | dreturn         | 从当前方法返回double                                         |
| 0xb0   | areturn         | 从当前方法返回对象引用                                       |
| 0xb1   | return          | 从当前方法返回void                                           |
| 0xb2   | getstatic       | 获取指定类的静态域, 并将其压入栈顶                           |
| 0xb3   | putstatic       | 为指定类的静态域赋值                                         |
| 0xb4   | getfield        | 获取指定类的实例域, 并将其压入栈顶                           |
| 0xb5   | putfield        | 为指定类的实例域赋值                                         |
| 0xb6   | invokevirtual   | 调用实例方法                                                 |
| 0xb7   | invokespecial   | 调用超类构建方法, 实例初始化方法, 私有方法                   |
| 0xb8   | invokestatic    | 调用静态方法                                                 |
| 0xb9   | invokeinterface | 调用接口方法                                                 |
| 0xba   | invokedynamic   | 调用动态方法                                                 |
| 0xbb   | new             | 创建一个对象, 并将其引用引用值压入栈顶                       |
| 0xbc   | newarray        | 创建一个指定的原始类型(如int, float, char等)的数组, 并将其引用值压入栈顶 |
| 0xbd   | anewarray       | 创建一个引用型(如类, 接口, 数组)的数组, 并将其引用值压入栈顶 |
| 0xbe   | arraylength     | 获取数组的长度值并压入栈顶                                   |
| 0xbf   | athrow          | 将栈顶的异常抛出                                             |
| 0xc0   | checkcast       | 检验类型转换, 检验未通过将抛出 ClassCastException            |
| 0xc1   | instanceof      | 检验对象是否是指定类的实际, 如果是将1压入栈顶, 否则将0压入栈顶 |
| 0xc2   | monitorenter    | 获得对象的锁, 用于同步方法或同步块                           |
| 0xc3   | monitorexit     | 释放对象的锁, 用于同步方法或同步块                           |
| 0xc4   | wide            | 扩展本地变量的宽度                                           |
| 0xc5   | multianewarray  | 创建指定类型和指定维度的多维数组(执行该指令时, 操作栈中必须包含各维度的长度值), 并将其引用压入栈顶 |
| 0xc6   | ifnull          | 为null时跳转                                                 |
| 0xc7   | ifnonnull       | 不为null时跳转                                               |
| 0xc8   | goto_w          | 无条件跳转(宽索引)                                           |
| 0xc9   | jsr_w           | 跳转至指定的32位offset位置, 并将jsr_w的下一条指令地址压入栈顶 |